{
  "name": "d31/adjacent-wildcards-preserve-candidates-and-order",
  "snapshot": {
    "format": "jsonspecs-snapshot",
    "formatVersion": 2,
    "specVersion": "1.0.0-rc.7",
    "exports": [
      "checks.main"
    ],
    "artifacts": {
      "checks.main": {
        "type": "pipeline",
        "steps": [
          "library.d31.adjacent"
        ]
      },
      "library.d31.adjacent": {
        "type": "rule",
        "operator": "not_empty",
        "field": "matrix[*][*].sku",
        "aggregate": {
          "mode": "ALL",
          "issueMode": "EACH"
        },
        "issue": {
          "level": "ERROR",
          "code": "D31.ADJACENT",
          "message": "failed"
        }
      }
    },
    "sourceHash": "086232042e9f2fcd53f65a0d3b12236e499cb65086d5c9fa2b8e836c3064f7d7"
  },
  "operators": [],
  "input": {
    "pipelineId": "checks.main",
    "payload": {
      "matrix": [
        [
          {
            "sku": "A"
          },
          {}
        ],
        [
          null,
          {
            "sku": "B"
          }
        ]
      ]
    }
  },
  "expected": {
    "status": "ERROR",
    "issues": [
      {
        "level": "ERROR",
        "code": "D31.ADJACENT",
        "message": "failed",
        "field": "matrix[0][1].sku",
        "ruleId": "library.d31.adjacent",
        "pipelineId": "checks.main"
      },
      {
        "level": "ERROR",
        "code": "D31.ADJACENT",
        "message": "failed",
        "field": "matrix[1][0].sku",
        "ruleId": "library.d31.adjacent",
        "pipelineId": "checks.main"
      }
    ],
    "ruleset": {
      "specVersion": "1.0.0-rc.7",
      "sourceHash": "086232042e9f2fcd53f65a0d3b12236e499cb65086d5c9fa2b8e836c3064f7d7"
    }
  }
}
