{
  "name": "d04/dot-matches-one-code-point",
  "snapshot": {
    "format": "jsonspecs-snapshot",
    "formatVersion": 2,
    "specVersion": "1.0.0-rc.7",
    "exports": [
      "checks.main"
    ],
    "artifacts": {
      "checks.main": {
        "type": "pipeline",
        "steps": [
          "library.r.dot"
        ]
      },
      "library.r.dot": {
        "type": "rule",
        "operator": "matches_regex",
        "field": "a",
        "value": "^.$",
        "issue": {
          "level": "ERROR",
          "code": "R10",
          "message": "failed"
        }
      }
    },
    "sourceHash": "1eaf29d2eba46acecadbc96f6cbf1444f4aeb61fd0162e1d540a28a98405a288"
  },
  "operators": [],
  "input": {
    "pipelineId": "checks.main",
    "payload": {
      "a": "😀"
    }
  },
  "expected": {
    "status": "OK",
    "issues": [],
    "ruleset": {
      "specVersion": "1.0.0-rc.7",
      "sourceHash": "1eaf29d2eba46acecadbc96f6cbf1444f4aeb61fd0162e1d540a28a98405a288"
    }
  }
}
