{
  "name": "d04/reject-backreference",
  "snapshot": {
    "format": "jsonspecs-snapshot",
    "formatVersion": 2,
    "specVersion": "1.0.0-rc.6",
    "exports": [
      "checks.main"
    ],
    "artifacts": {
      "checks.main": {
        "type": "pipeline",
        "steps": [
          "library.r.b"
        ]
      },
      "library.r.b": {
        "type": "rule",
        "operator": "matches_regex",
        "field": "a",
        "value": "^(a)\\1$",
        "issue": {
          "level": "ERROR",
          "code": "R2",
          "message": "failed"
        }
      }
    },
    "sourceHash": "db1100740941fda4f0d9673c268ef2401761c8953e4a00cedd7b6e24d100ac64"
  },
  "operators": [],
  "expected": {
    "verdict": "reject"
  }
}
