{
  "name": "d10/unknown-operator-with-empty-input-name-has-no-operator-identifier",
  "snapshot": {
    "format": "jsonspecs-snapshot",
    "formatVersion": 2,
    "specVersion": "1.0.0-rc.7",
    "exports": [
      "checks.main"
    ],
    "artifacts": {
      "checks.main": {
        "type": "pipeline",
        "steps": [
          "library.c.empty-input"
        ]
      },
      "library.c.empty-input": {
        "type": "rule",
        "operator": "custom_x",
        "inputs": {
          "": "a"
        },
        "issue": {
          "level": "ERROR",
          "code": "C4",
          "message": "failed"
        }
      }
    },
    "sourceHash": "0e5c0409c0b1c155154d952a61cb34957e1e1457085ccebb1617be1fd89e84e6"
  },
  "operators": [],
  "expected": {
    "verdict": "reject"
  }
}
