{
  "name": "d11/reject-partial-issue-object",
  "snapshot": {
    "format": "jsonspecs-snapshot",
    "formatVersion": 2,
    "specVersion": "1.0.0-rc.4",
    "exports": [
      "checks.main"
    ],
    "sourceHash": "17730d66906f30f9106d934bd89f56d85994362ab26312dd02c557049fcb15cb",
    "artifacts": [
      {
        "id": "library.x.p",
        "type": "rule",
        "operator": "not_empty",
        "field": "a",
        "issue": {
          "code": "NOPE",
          "message": "failed"
        }
      },
      {
        "id": "library.x.ok",
        "type": "rule",
        "operator": "not_empty",
        "field": "a",
        "issue": {
          "level": "ERROR",
          "code": "X6",
          "message": "failed"
        }
      },
      {
        "id": "checks.main",
        "type": "pipeline",
        "strict": false,
        "flow": [
          {
            "rule": "library.x.ok"
          }
        ]
      }
    ]
  },
  "operators": [],
  "expected": {
    "verdict": "reject"
  }
}
