{
  "name": "d11/reject-all-with-issue-without-issue-mode",
  "snapshot": {
    "format": "jsonspecs-snapshot",
    "formatVersion": 2,
    "specVersion": "1.0.0-rc.7",
    "exports": [
      "checks.main"
    ],
    "artifacts": {
      "checks.main": {
        "type": "pipeline",
        "steps": [
          "library.d20.bad2"
        ]
      },
      "library.d20.bad2": {
        "type": "rule",
        "operator": "greater_than",
        "field": "x[*].v",
        "value": 1,
        "aggregate": {
          "mode": "ALL"
        },
        "issue": {
          "level": "ERROR",
          "code": "D20.X2",
          "message": "failed"
        }
      }
    },
    "sourceHash": "68290b49e90a35481f7b1908b49b09cefd19d594e86fa232abb7922a54e27281"
  },
  "operators": [],
  "expected": {
    "verdict": "reject"
  }
}
