{
  "name": "d05/odometer-order-two-wildcards",
  "snapshot": {
    "format": "jsonspecs-snapshot",
    "formatVersion": 2,
    "specVersion": "1.0.0-rc.3",
    "sourceHash": "8bf1f8c91e73a4a2b6ea5d16e693b74c143bafe1a4d03af6a5b1b93a30d1c1c3",
    "artifacts": [
      {
        "id": "library.o.odo",
        "type": "rule",
        "description": "fixture rule",
        "operator": "greater_than",
        "field": "m[*].n[*].v",
        "value": 10,
        "aggregate": {
          "mode": "ALL",
          "issueMode": "EACH"
        },
        "issue": {
          "level": "ERROR",
          "code": "O2",
          "message": "failed"
        }
      },
      {
        "id": "checks.main",
        "type": "pipeline",
        "description": "fixture pipeline",
        "entrypoint": true,
        "strict": false,
        "flow": [
          {
            "rule": "library.o.odo"
          }
        ]
      }
    ]
  },
  "operators": [],
  "input": {
    "pipelineId": "checks.main",
    "payload": {
      "m": [
        {
          "n": [
            {
              "v": 1
            },
            {
              "v": 2
            }
          ]
        },
        {
          "n": [
            {
              "v": 3
            }
          ]
        }
      ]
    }
  },
  "expected": {
    "status": "ERROR",
    "control": "STOP",
    "issues": [
      {
        "kind": "ISSUE",
        "level": "ERROR",
        "code": "O2",
        "message": "failed",
        "field": "m[0].n[0].v",
        "ruleId": "library.o.odo",
        "pipelineId": "checks.main",
        "expected": 10,
        "actual": 1
      },
      {
        "kind": "ISSUE",
        "level": "ERROR",
        "code": "O2",
        "message": "failed",
        "field": "m[0].n[1].v",
        "ruleId": "library.o.odo",
        "pipelineId": "checks.main",
        "expected": 10,
        "actual": 2
      },
      {
        "kind": "ISSUE",
        "level": "ERROR",
        "code": "O2",
        "message": "failed",
        "field": "m[1].n[0].v",
        "ruleId": "library.o.odo",
        "pipelineId": "checks.main",
        "expected": 10,
        "actual": 3
      }
    ],
    "ruleset": {
      "specVersion": "1.0.0-rc.3",
      "sourceHash": "8bf1f8c91e73a4a2b6ea5d16e693b74c143bafe1a4d03af6a5b1b93a30d1c1c3"
    }
  }
}
